jumpcutter/__main__.py
jumpcutter/clip.py
jumpcutter-0.1.6.dist-info/entry_points.txt
jumpcutter-0.1.6.dist-info/LICENSE
jumpcutter-0.1.6.dist-info/WHEEL
jumpcutter-0.1.6.dist-info/METADATA
jumpcutter-0.1.6.dist-info/RECORD
