Metadata-Version: 2.1
Name: jumpcutter
Version: 0.1.6
Summary: Jumpcut silent parts of your videos automagically
Home-page: https://github.com/kivancyuksel/jumpcutter.git
License: MIT
Author: Kivanc Yuksel
Author-email: emkademy@gmail.com
Requires-Python: >=3.6,<4.0
Classifier: Development Status :: 4 - Beta
Classifier: License :: OSI Approved :: MIT License
Classifier: Natural Language :: English
Classifier: Programming Language :: Python :: 3
Classifier: Programming Language :: Python :: 3.6
Classifier: Programming Language :: Python :: 3.7
Classifier: Programming Language :: Python :: 3.8
Classifier: Programming Language :: Python :: 3.9
Classifier: Topic :: Multimedia :: Video
Requires-Dist: moviepy (>=1.0.3,<1.1.0)
Requires-Dist: tqdm (>=4.60.0,<4.61.0)
Project-URL: Repository, https://github.com/kivancyuksel/jumpcutter.git
